{
  "gameId": "0022100826",
  "gameCode": "20220209/CHICHA",
  "gameStatus": 3,
  "gameStatusText": "Final",
  "gameDateTimeEst": "2022-02-09T19:30:00Z",
  "gameDateTimeUTC": "2022-02-10T00:30:00Z",
  "homeTeamTime": "2022-02-09T19:30:00Z",
  "day": "Wed",
  "monthNum": 2,
  "weekNumber": 17,
  "ifNecessary": false,
  "seriesGameNumber": "",
  "seriesText": "",
  "arenaName": "Spectrum Center",
  "arenaState": "NC",
  "arenaCity": "Charlotte",
  "postponedStatus": "A",
  "homeTeam": {
    "teamId": 1610612766,
    "teamName": "Hornets",
    "teamCity": "Charlotte",
    "teamTricode": "CHA",
    "teamSlug": "hornets",
    "wins": 28,
    "losses": 28,
    "score": 109,
    "seed": 0
  },
  "awayTeam": {
    "teamId": 1610612741,
    "teamName": "Bulls",
    "teamCity": "Chicago",
    "teamTricode": "CHI",
    "teamSlug": "bulls",
    "wins": 34,
    "losses": 21,
    "score": 121,
    "seed": 0
  }
}