{
  "gameId": "0022100972",
  "gameCode": "20220307/UTADAL",
  "gameStatus": 3,
  "gameStatusText": "Final",
  "gameDateTimeEst": "2022-03-07T20:30:00Z",
  "gameDateTimeUTC": "2022-03-08T01:30:00Z",
  "homeTeamTime": "2022-03-07T19:30:00Z",
  "day": "Mon",
  "monthNum": 3,
  "weekNumber": 21,
  "ifNecessary": false,
  "seriesGameNumber": "",
  "seriesText": "",
  "arenaName": "American Airlines Center",
  "arenaState": "TX",
  "arenaCity": "Dallas",
  "postponedStatus": "A",
  "homeTeam": {
    "teamId": 1610612742,
    "teamName": "Mavericks",
    "teamCity": "Dallas",
    "teamTricode": "DAL",
    "teamSlug": "mavericks",
    "wins": 40,
    "losses": 25,
    "score": 111,
    "seed": 0
  },
  "awayTeam": {
    "teamId": 1610612762,
    "teamName": "Jazz",
    "teamCity": "Utah",
    "teamTricode": "UTA",
    "teamSlug": "jazz",
    "wins": 40,
    "losses": 24,
    "score": 103,
    "seed": 0
  }
}