{
  "gameId": "0022100894",
  "gameCode": "20220224/GSWPOR",
  "gameStatus": 3,
  "gameStatusText": "Final",
  "gameDateTimeEst": "2022-02-24T22:00:00Z",
  "gameDateTimeUTC": "2022-02-25T03:00:00Z",
  "homeTeamTime": "2022-02-24T19:00:00Z",
  "day": "Thu",
  "monthNum": 2,
  "weekNumber": 19,
  "ifNecessary": false,
  "seriesGameNumber": "",
  "seriesText": "",
  "arenaName": "Moda Center",
  "arenaState": "OR",
  "arenaCity": "Portland",
  "postponedStatus": "A",
  "homeTeam": {
    "teamId": 1610612757,
    "teamName": "Trail Blazers",
    "teamCity": "Portland",
    "teamTricode": "POR",
    "teamSlug": "blazers",
    "wins": 25,
    "losses": 35,
    "score": 95,
    "seed": 0
  },
  "awayTeam": {
    "teamId": 1610612744,
    "teamName": "Warriors",
    "teamCity": "Golden State",
    "teamTricode": "GSW",
    "teamSlug": "warriors",
    "wins": 43,
    "losses": 17,
    "score": 132,
    "seed": 0
  }
}